wink_sdk_booking/__init__.py
wink_sdk_booking/api_client.py
wink_sdk_booking/api_response.py
wink_sdk_booking/configuration.py
wink_sdk_booking/exceptions.py
wink_sdk_booking/py.typed
wink_sdk_booking/rest.py
wink_sdk_booking/api/__init__.py
wink_sdk_booking/api/booking_api.py
wink_sdk_booking/api/checkout_api.py
wink_sdk_booking/api/consumer_booking_api.py
wink_sdk_booking/api/review_api.py
wink_sdk_booking/api/shopping_cart_api.py
wink_sdk_booking/models/__init__.py
wink_sdk_booking/models/address_authenticated_entity.py
wink_sdk_booking/models/address_booker.py
wink_sdk_booking/models/aggregate_descriptor_booker.py
wink_sdk_booking/models/ancillary_request_authenticated_entity.py
wink_sdk_booking/models/authenticated_user_booker.py
wink_sdk_booking/models/bed_authenticated_entity.py
wink_sdk_booking/models/bed_booker.py
wink_sdk_booking/models/bedroom_authenticated_entity.py
wink_sdk_booking/models/bedroom_booker.py
wink_sdk_booking/models/bedroom_configuration_authenticated_entity.py
wink_sdk_booking/models/bedroom_configuration_booker.py
wink_sdk_booking/models/beneficiary_booker.py
wink_sdk_booking/models/beneficiary_charge_booker.py
wink_sdk_booking/models/booking_ancillary_authenticated_entity.py
wink_sdk_booking/models/booking_ancillary_booker.py
wink_sdk_booking/models/booking_booker.py
wink_sdk_booking/models/booking_contract_booker.py
wink_sdk_booking/models/booking_contract_item_booker.py
wink_sdk_booking/models/booking_contract_payment_details_booker.py
wink_sdk_booking/models/booking_itinerary_booker.py
wink_sdk_booking/models/booking_itinerary_room_configuration_booker.py
wink_sdk_booking/models/booking_itinerary_room_configuration_child_booker.py
wink_sdk_booking/models/booking_user_booker.py
wink_sdk_booking/models/booking_user_request_authenticated_entity.py
wink_sdk_booking/models/booking_user_session_booker.py
wink_sdk_booking/models/booking_view_booker.py
wink_sdk_booking/models/boolean_response_authenticated_entity.py
wink_sdk_booking-0.0.57.dist-info/licenses/LICENSE
wink_sdk_booking-0.0.57.dist-info/METADATA
wink_sdk_booking-0.0.57.dist-info/WHEEL
wink_sdk_booking-0.0.57.dist-info/top_level.txt
wink_sdk_booking-0.0.57.dist-info/RECORD
